MANIFEST.in
README.rst
VERSION
setup.py
recip/__init__.py
recip/article.sage
recip/basic.py
recip/basic.sage
recip/bissonstreng.py
recip/bissonstreng.sage
recip/bls.py
recip/bls.sage
recip/class_polynomials.py
recip/class_polynomials.sage
recip/cm_types.py
recip/cm_types.sage
recip/create_py_files_for_doc.sage.py
recip/denominators.py
recip/denominators.sage
recip/find_class_invariant.py
recip/find_class_invariant.sage
recip/igusa_invariants.py
recip/igusa_invariants.sage
recip/list_fields.py
recip/list_fields.sage
recip/one_cython_file.pyx
recip/orders.py
recip/orders.sage
recip/period_matrices.py
recip/period_matrices.sage
recip/polynomials.py
recip/polynomials.sage
recip/recip.sage
recip/recip_online.sage
recip/symplectic_matrices.py
recip/symplectic_matrices.sage
recip/theta_trans.py
recip/theta_trans.sage
recip.egg-info/PKG-INFO
recip.egg-info/SOURCES.txt
recip.egg-info/dependency_links.txt
recip.egg-info/requires.txt
recip.egg-info/top_level.txt