Metadata-Version: 1.1
Name: recip
Version: 3.0.1
Summary: CM SageMath code
Home-page: https://github.com/mstreng/recip
Author: Marco Streng
Author-email: marco.streng@gmail.com
License: GPLv2+
Keywords: SageMath,CM,Complex Multiplication,Siegel modular forms,elliptic curve,hyperelliptic curve,isogeny
Platform: UNKNOWN
Classifier: Development Status :: 4 - Beta
Classifier: Intended Audience :: Science/Research
Classifier: Topic :: Software Development :: Build Tools
Classifier: Topic :: Scientific/Engineering :: Mathematics
Classifier: License :: OSI Approved :: GNU General Public License v2 or later (GPLv2+)
Classifier: Programming Language :: Python :: 2.7
